pgreaper/__init__.py
pgreaper/_globals.py
pgreaper/config.py
pgreaper/pandas.py
pgreaper/testing.py
pgreaper/cli/__init__.py
pgreaper/cli/copy.py
pgreaper/cli/datareaper.py
pgreaper/core/__init__.py
pgreaper/core/_base_table.py
pgreaper/core/_table.py
pgreaper/core/column_list.py
pgreaper/core/mappings.py
pgreaper/core/schema.py
pgreaper/core/table.c
pgreaper/core/table.cp36-win_amd64.pyd
pgreaper/core/table_out.py
pgreaper/data/pg_keywords.txt
pgreaper/extras/__init__.py
pgreaper/extras/json_extras.py
pgreaper/html/__init__.py
pgreaper/html/_parser.py
pgreaper/html/parser.py
pgreaper/html/table.py
pgreaper/html/tree.py
pgreaper/io/__init__.py
pgreaper/io/json_reader.py
pgreaper/io/json_tools.cp36-win_amd64.pyd
pgreaper/io/json_tools.cpp
pgreaper/io/zip.py
pgreaper/notebook/__init__.py
pgreaper/notebook/css.py
pgreaper/notebook/pgreaper.css
pgreaper/plpgsql/flatten_json.sql
pgreaper/plpgsql/sanitize_name.sql
pgreaper/postgres/__init__.py
pgreaper/postgres/conn.py
pgreaper/postgres/csv_loader.py
pgreaper/postgres/database.py
pgreaper/postgres/json_loader.py
pgreaper/postgres/loader.py
pgreaper/sqlite/__init__.py
pgreaper/sqlite/to_postgres.py
pgreaper-1.0.0a2.dist-info/DESCRIPTION.rst
pgreaper-1.0.0a2.dist-info/METADATA
pgreaper-1.0.0a2.dist-info/RECORD
pgreaper-1.0.0a2.dist-info/WHEEL
pgreaper-1.0.0a2.dist-info/entry_points.txt
pgreaper-1.0.0a2.dist-info/metadata.json
pgreaper-1.0.0a2.dist-info/top_level.txt
